odoo/addons/reports_font_size/README.rst
odoo/addons/reports_font_size/__manifest__.py
odoo/addons/reports_font_size/static/description/icon.png
odoo/addons/reports_font_size/static/src/scss/_variables.scss
odoo/addons/reports_font_size/views/reports_font_size.xml
odoo14_addon_reports_font_size-14.0.1.0.0.dist-info/METADATA
odoo14_addon_reports_font_size-14.0.1.0.0.dist-info/WHEEL
odoo14_addon_reports_font_size-14.0.1.0.0.dist-info/top_level.txt
odoo14_addon_reports_font_size-14.0.1.0.0.dist-info/RECORD
